pyms/__init__.py
pyms/__main__.py
pyms/dunn_test.py
pyms/pyms.py
pyms_plot-0.9.0.dist-info/LICENSE
pyms_plot-0.9.0.dist-info/METADATA
pyms_plot-0.9.0.dist-info/WHEEL
pyms_plot-0.9.0.dist-info/entry_points.txt
pyms_plot-0.9.0.dist-info/top_level.txt
pyms_plot-0.9.0.dist-info/RECORD
