Metadata-Version: 2.1
Name: pyms-plot
Version: 0.9.0
Summary: PyMS (Python for Mycorrhizal Symbiosis)
Home-page: https://github.com/jschnab/pyms
Author: Jonathan Schnabel
Author-email: jonathan.schnabel31@gmail.com
License: GNU General Public License v3.0
Keywords: arbuscular mycorrhizal symbiosis data analysis statistics
Platform: UNKNOWN
Classifier: Intended Audience :: Science/Research
Classifier: Topic :: Scientific/Engineering
Classifier: Programming Language :: Python :: 3.5
Requires-Python: >=3.5.2
Requires-Dist: numpy
Requires-Dist: scipy
Requires-Dist: pandas
Requires-Dist: matplotlib
Requires-Dist: statsmodels
